{
  "main": {
    "id": "66f71bbfdc3c031b",
    "type": "split",
    "children": [
      {
        "id": "6d254cfe6106185e",
        "type": "tabs",
        "children": [
          {
            "id": "557c4e628455cb14",
            "type": "leaf",
            "state": {
              "type": "markdown",
              "state": {
                "file": "CS&AI学习/机器学习.md",
                "mode": "source",
                "source": true
              },
              "icon": "lucide-file",
              "title": "机器学习"
            }
          }
        ]
      }
    ],
    "direction": "vertical"
  },
  "left": {
    "id": "c226baed6005d8f7",
    "type": "split",
    "children": [
      {
        "id": "18d209b71218564c",
        "type": "tabs",
        "children": [
          {
            "id": "ada2f3d4dc930899",
            "type": "leaf",
            "state": {
              "type": "file-explorer",
              "state": {
                "sortOrder": "alphabetical",
                "autoReveal": false
              },
              "icon": "lucide-folder-closed",
              "title": "文件列表"
            }
          },
          {
            "id": "a43b1c16c4036043",
            "type": "leaf",
            "state": {
              "type": "search",
              "state": {
                "query": "path:\"CS&AI学习/image/\" ",
                "matchingCase": false,
                "explainSearch": false,
                "collapseAll": false,
                "extraContext": false,
                "sortOrder": "alphabetical"
              },
              "icon": "lucide-search",
              "title": "搜索"
            }
          },
          {
            "id": "71f35e356678143b",
            "type": "leaf",
            "state": {
              "type": "bookmarks",
              "state": {},
              "icon": "lucide-bookmark",
              "title": "书签"
            }
          }
        ]
      }
    ],
    "direction": "horizontal",
    "width": 300
  },
  "right": {
    "id": "8ecf4caaff0dbfaf",
    "type": "split",
    "children": [
      {
        "id": "54a55f430799fe66",
        "type": "tabs",
        "children": [
          {
            "id": "48dcab4f3cdf34cb",
            "type": "leaf",
            "state": {
              "type": "backlink",
              "state": {
                "file": "AI学习/搜索.md",
                "collapseAll": false,
                "extraContext": false,
                "sortOrder": "alphabetical",
                "showSearch": false,
                "searchQuery": "",
                "backlinkCollapsed": false,
                "unlinkedCollapsed": true
              },
              "icon": "links-coming-in",
              "title": "搜索 的反向链接列表"
            }
          },
          {
            "id": "4137dacfb6c3a381",
            "type": "leaf",
            "state": {
              "type": "outgoing-link",
              "state": {
                "file": "AI学习/搜索.md",
                "linksCollapsed": false,
                "unlinkedCollapsed": true
              },
              "icon": "links-going-out",
              "title": "搜索 的出链列表"
            }
          },
          {
            "id": "2f3e8cea6e6cfb55",
            "type": "leaf",
            "state": {
              "type": "tag",
              "state": {
                "sortOrder": "frequency",
                "useHierarchy": true,
                "showSearch": false,
                "searchQuery": ""
              },
              "icon": "lucide-tags",
              "title": "标签"
            }
          },
          {
            "id": "1cadb7e4dd651d92",
            "type": "leaf",
            "state": {
              "type": "all-properties",
              "state": {
                "sortOrder": "frequency",
                "showSearch": false,
                "searchQuery": ""
              },
              "icon": "lucide-archive",
              "title": "添加笔记属性"
            }
          },
          {
            "id": "f80db6997ed08218",
            "type": "leaf",
            "state": {
              "type": "outline",
              "state": {
                "file": "AI学习/搜索.md",
                "followCursor": false,
                "showSearch": false,
                "searchQuery": ""
              },
              "icon": "lucide-list",
              "title": "搜索 的大纲"
            }
          },
          {
            "id": "8580119b5f3ebb51",
            "type": "leaf",
            "state": {
              "type": "calendar",
              "state": {},
              "icon": "calendar-with-checkmark",
              "title": "Calendar"
            }
          },
          {
            "id": "2efcebaac66c20b0",
            "type": "leaf",
            "state": {
              "type": "file-properties",
              "state": {
                "file": "CS&AI学习/程设.md"
              },
              "icon": "lucide-info",
              "title": "程设的笔记属性"
            }
          },
          {
            "id": "c6287249d1f839c9",
            "type": "leaf",
            "state": {
              "type": "git-view",
              "state": {},
              "icon": "git-pull-request",
              "title": "Source Control"
            }
          }
        ],
        "currentTab": 7
      }
    ],
    "direction": "horizontal",
    "width": 300,
    "collapsed": true
  },
  "left-ribbon": {
    "hiddenItems": {
      "switcher:打开快速切换": false,
      "graph:查看关系图谱": false,
      "canvas:新建白板": false,
      "daily-notes:打开/创建今天的日记": false,
      "templates:插入模板": false,
      "command-palette:打开命令面板": false,
      "bases:新建数据库": false,
      "table-editor-obsidian:Advanced Tables Toolbar": false,
      "obsidian-excalidraw-plugin:New drawing": false,
      "obsidian-git:Open Git source control": false
    }
  },
  "active": "557c4e628455cb14",
  "lastOpenFiles": [
    "CS&AI学习/程设.md",
    "CS&AI学习/机器学习.md",
    "CS&AI学习/~syncthing~程设.md.tmp",
    "CS&AI学习/数据结构.md",
    "CS&AI学习/人工智能引论.md",
    "CS&AI学习/面向对象.md",
    "CS&AI学习/image/bs.png",
    "其他课程/国社上.md",
    "其他课程/国社上.sync-conflict-20260330-213742-RIY3QVG.md",
    "其他课程/~syncthing~国社上.sync-conflict-20260330-213742-RIY3QVG.md.tmp",
    "CS&AI学习/image/algo.jpg",
    "CS&AI学习/人工智能引论笔记/搜索.md",
    "CS&AI学习/image/K.png",
    "README.md",
    "CS&AI学习/CV导.md",
    "新建 文本文档.txt",
    "CS&AI学习/notttte.zip",
    "CS&AI学习/博弈（game）.zip",
    "CS&AI学习/博弈（game）.md",
    "CS&AI学习/人工智能引论笔记/CSP(Constraint Satisfaction Problems).md",
    "CS&AI学习/CS中的数学.md",
    "CS&AI学习/~syncthing~博弈（game）.md.tmp",
    "CS&AI学习/人工智能引论笔记/~syncthing~搜索.md.tmp",
    "CS&AI学习/CSP(Constraint Satisfaction Problems).md",
    "课程/课程安排.md",
    "CS&AI学习/image/filter-example.png",
    "CS&AI学习/image/屏幕截图 2026-03-17 155455.png",
    "CS&AI学习/程设.sync-conflict-20260311-213006-FF3QXEW.md",
    "CS&AI学习/~syncthing~CS中的数学.md.tmp",
    "().md",
    "CS&AI学习/人工智能引论笔记",
    "CS&AI学习/image/~syncthing~algo.jpg.tmp",
    "CS&AI学习/image/随机排列.png",
    "CS&AI学习/image/屏幕截图 2026-03-05 174344.png",
    "CS&AI学习/image/ds1.png",
    "CS&AI学习/image/屏幕截图 2026-03-05 000801.png",
    "CPS.md",
    "AI学习/Excalidraw/Drawing 2026-03-02 17.07.38.excalidraw.md",
    "CS&AI学习/Excalidraw/Drawing 2026-03-02 17.41.54.excalidraw.md",
    "AI学习/数据结构.sync-conflict-20260302-232004-RIY3QVG.md",
    "AI学习/搜索.sync-conflict-20260302-232054-RIY3QVG.md"
  ]
}